filterimage/__init__.py
filterimage/filterimage.py
filterimage-0.1.2.dist-info/LICENSE
filterimage-0.1.2.dist-info/METADATA
filterimage-0.1.2.dist-info/WHEEL
filterimage-0.1.2.dist-info/top_level.txt
filterimage-0.1.2.dist-info/RECORD
