Metadata-Version: 2.1
Name: filterimage
Version: 0.1.2
Summary: Python package for my filterimage.
Home-page: https://github.com/darnell-love27/Image_Filters
Author: Darnell Love
Author-email: darnell.love@bison.howard.edu
Classifier: Programming Language :: Python :: 3
Classifier: License :: OSI Approved :: MIT License
Classifier: Operating System :: OS Independent
Requires-Python: >=3
License-File: LICENSE
